gemini_self_protector/__init__.py
gemini_self_protector/_audit.py
gemini_self_protector/_behavior.py
gemini_self_protector/_cli.py
gemini_self_protector/_config.py
gemini_self_protector/_gemini.py
gemini_self_protector/_gui.py
gemini_self_protector/_logger.py
gemini_self_protector/_model.py
gemini_self_protector/_protect.py
gemini_self_protector/_template.py
gemini_self_protector/_utils.py
gemini_self_protector/gemini_self_protector.py
gemini_self_protector/resource/assets/css/dark.css
gemini_self_protector/resource/assets/css/install.css
gemini_self_protector/resource/assets/css/style.css
gemini_self_protector/resource/assets/fonts/datta/datta-icon.css
gemini_self_protector/resource/assets/fonts/datta/fonts/pct.eot
gemini_self_protector/resource/assets/fonts/datta/fonts/pct.svg
gemini_self_protector/resource/assets/fonts/datta/fonts/pct.ttf
gemini_self_protector/resource/assets/fonts/datta/fonts/pct.woff
gemini_self_protector/resource/assets/fonts/feather/css/feather.css
gemini_self_protector/resource/assets/fonts/feather/fonts/feather.eot
gemini_self_protector/resource/assets/fonts/feather/fonts/feather.svg
gemini_self_protector/resource/assets/fonts/feather/fonts/feather.ttf
gemini_self_protector/resource/assets/fonts/feather/fonts/feather.woff
gemini_self_protector/resource/assets/fonts/fontawesome/css/fontawesome-all.min.css
gemini_self_protector/resource/assets/fonts/fontawesome/webfonts/fa-brands-400.eot
gemini_self_protector/resource/assets/fonts/fontawesome/webfonts/fa-brands-400.svg
gemini_self_protector/resource/assets/fonts/fontawesome/webfonts/fa-brands-400.ttf
gemini_self_protector/resource/assets/fonts/fontawesome/webfonts/fa-brands-400.woff
gemini_self_protector/resource/assets/fonts/fontawesome/webfonts/fa-brands-400.woff2
gemini_self_protector/resource/assets/fonts/fontawesome/webfonts/fa-regular-400.eot
gemini_self_protector/resource/assets/fonts/fontawesome/webfonts/fa-regular-400.svg
gemini_self_protector-0.1.7.dist-info/LICENSE
gemini_self_protector-0.1.7.dist-info/METADATA
gemini_self_protector-0.1.7.dist-info/WHEEL
gemini_self_protector-0.1.7.dist-info/RECORD
