Metadata-Version: 2.1
Name: gemini_self_protector
Version: 0.1.7
Summary: Runtime Application Self-Protection
License: MIT
Author: lethanhphuc
Requires-Python: >=3.9,<4.0
Classifier: License :: OSI Approved :: MIT License
Classifier: Programming Language :: Python :: 3
Classifier: Programming Language :: Python :: 3.9
Classifier: Programming Language :: Python :: 3.10
Classifier: Programming Language :: Python :: 3.11
Classifier: Programming Language :: Python :: 3.12
Classifier: Programming Language :: Python :: 3.13
Requires-Dist: argon2-cffi (>=23.1.0,<24.0.0)
Requires-Dist: cachetools (>=5.3.1,<6.0.0)
Requires-Dist: colorlog (>=6.7.0,<7.0.0)
Requires-Dist: flask-sqlalchemy (>=3.0.3,<4.0.0)
Requires-Dist: passlib (>=1.7.4,<2.0.0)
Requires-Dist: psutil (>=6.1.0,<7.0.0)
Requires-Dist: pyjwt (>=2.7.0,<3.0.0)
Requires-Dist: pyyaml (>=6.0,<7.0)
Requires-Dist: requests (>=2.31.0,<3.0.0)
Requires-Dist: tqdm (>=4.66.1,<5.0.0)
